MANIFEST.in
README.rst
setup.py
aliyun_python_sdk_aegis.egg-info/PKG-INFO
aliyun_python_sdk_aegis.egg-info/SOURCES.txt
aliyun_python_sdk_aegis.egg-info/dependency_links.txt
aliyun_python_sdk_aegis.egg-info/requires.txt
aliyun_python_sdk_aegis.egg-info/top_level.txt
aliyunsdkaegis/__init__.py
aliyunsdkaegis/request/__init__.py
aliyunsdkaegis/request/v20161111/AutoUpgradeSasRequest.py
aliyunsdkaegis/request/v20161111/AutoUpgradeToSasAdvancedVersionRequest.py
aliyunsdkaegis/request/v20161111/BatchDeleteWhiteListRequest.py
aliyunsdkaegis/request/v20161111/CanTrySasRequest.py
aliyunsdkaegis/request/v20161111/CreatScreenSettingRequest.py
aliyunsdkaegis/request/v20161111/CreateInstanceRequest.py
aliyunsdkaegis/request/v20161111/CreateLogQueryRequest.py
aliyunsdkaegis/request/v20161111/CreateOrUpdateDataSourceRequest.py
aliyunsdkaegis/request/v20161111/CreateOrUpdateDingTalkRequest.py
aliyunsdkaegis/request/v20161111/CreateOrUpdateGroupRequest.py
aliyunsdkaegis/request/v20161111/CreateOrUpdateJoinRuleRequest.py
aliyunsdkaegis/request/v20161111/CreateOrUpdateRuleRequest.py
aliyunsdkaegis/request/v20161111/CreateSuspiciousExportRequest.py
aliyunsdkaegis/request/v20161111/CreateUserSettingRequest.py
aliyunsdkaegis/request/v20161111/CreateUserWhiteListRequest.py
aliyunsdkaegis/request/v20161111/CreateVulWhitelistRequest.py
aliyunsdkaegis/request/v20161111/DeleteDingTalkRequest.py
aliyunsdkaegis/request/v20161111/DeleteJoinRuleRequest.py
aliyunsdkaegis/request/v20161111/DeleteLogQueryRequest.py
aliyunsdkaegis/request/v20161111/DeleteRuleGroupRequest.py
aliyunsdkaegis/request/v20161111/DeleteRuleRequest.py
aliyunsdkaegis/request/v20161111/DeleteScreenSettingRequest.py
aliyunsdkaegis/request/v20161111/DeleteSearchConditionRequest.py
aliyunsdkaegis/request/v20161111/DeleteStrategyRequest.py
aliyunsdkaegis/request/v20161111/DeleteVulBatchRequest.py
aliyunsdkaegis/request/v20161111/DeleteVulWhitelistRequest.py
aliyunsdkaegis/request/v20161111/DescribeAgentInstallStatusRequest.py
aliyunsdkaegis/request/v20161111/DescribeAlarmEventDetailRequest.py
aliyunsdkaegis/request/v20161111/DescribeAlarmEventListRequest.py
aliyunsdkaegis/request/v20161111/DescribeAllRegionsStatisticsRequest.py
